resotoui/__init__.py
resotoui/ui/index.apple-touch-icon.png
resotoui/ui/index.audio.worklet.js
resotoui/ui/index.html
resotoui/ui/index.icon.png
resotoui/ui/index.js
resotoui/ui/index.pck
resotoui/ui/index.png
resotoui/ui/index.wasm
resotoui-3.7.1.dist-info/METADATA
resotoui-3.7.1.dist-info/WHEEL
resotoui-3.7.1.dist-info/top_level.txt
resotoui-3.7.1.dist-info/RECORD
